tradata_perf/__init__.py
tradata_perf/logger.py
tradata_perf/decorators/__init__.py
tradata_perf/decorators/metrics.py
tradata_perf/decorators/performance.py
tradata_perf/http/__init__.py
tradata_perf/http/optimized_client.py
tradata_perf/middleware/__init__.py
tradata_perf/middleware/cache.py
tradata_perf/middleware/performance.py
tradata_perf/monitoring/__init__.py
tradata_perf/monitoring/event_system.py
tradata_perf/monitoring/health_checker.py
tradata_perf/monitoring/metrics_collector.py
tradata_perf/monitoring/performance_monitor.py
tradata_perf-0.2.1.dist-info/licenses/LICENSE
tradata_perf-0.2.1.dist-info/METADATA
tradata_perf-0.2.1.dist-info/WHEEL
tradata_perf-0.2.1.dist-info/top_level.txt
tradata_perf-0.2.1.dist-info/RECORD
