Metadata-Version: 2.4
Name: tradata-perf
Version: 0.2.1
Summary: High-performance monitoring and optimization toolkit for trading applications
Author-email: Tradata Team <team@tradata.com>
License: MIT
Project-URL: Homepage, https://github.com/tradata/tradata-perf-py
Project-URL: Documentation, https://github.com/tradata/tradata-perf-py#readme
Project-URL: Repository, https://github.com/tradata/tradata-perf-py
Project-URL: Bug Tracker, https://github.com/tradata/tradata-perf-py/issues
Classifier: Development Status :: 4 - Beta
Classifier: Intended Audience :: Developers
Classifier: License :: OSI Approved :: MIT License
Classifier: Programming Language :: Python :: 3
Classifier: Programming Language :: Python :: 3.8
Classifier: Programming Language :: Python :: 3.9
Classifier: Programming Language :: Python :: 3.10
Classifier: Programming Language :: Python :: 3.11
Classifier: Topic :: System :: Monitoring
Classifier: Topic :: Software Development :: Libraries :: Python Modules
Classifier: Topic :: Internet :: WWW/HTTP :: HTTP Servers
Classifier: Topic :: Scientific/Engineering :: Information Analysis
Requires-Python: >=3.8
License-File: LICENSE
Requires-Dist: fastapi>=0.68.0
Requires-Dist: httpx>=0.23.0
Requires-Dist: psutil>=5.8.0
Requires-Dist: tradata-core>=0.2.0
Provides-Extra: dev
Requires-Dist: pytest>=6.0; extra == "dev"
Requires-Dist: pytest-cov; extra == "dev"
Requires-Dist: pytest-benchmark; extra == "dev"
Requires-Dist: pytest-asyncio; extra == "dev"
Requires-Dist: black; extra == "dev"
Requires-Dist: flake8; extra == "dev"
Requires-Dist: mypy; extra == "dev"
Requires-Dist: build; extra == "dev"
Provides-Extra: advanced
Requires-Dist: py-spy>=0.3.0; extra == "advanced"
Requires-Dist: memory-profiler>=0.60.0; extra == "advanced"
Requires-Dist: prometheus-client>=0.14.0; extra == "advanced"
Dynamic: license-file
